Metadata-Version: 2.1
Name: sigilyph
Version: 0.5.4
Summary: Text Front for TTS
Home-page: https://github.com/yixiangchen1995/python-Sigilyph
Author: Yixiang Chen
Author-email: <yixiangchen1995@gmail.com>
License: MIT
Keywords: python,first package
Classifier: Development Status :: 3 - Alpha
Classifier: Intended Audience :: Developers
Classifier: Programming Language :: Python
Classifier: Programming Language :: Python :: 3.10
Requires-Dist: g2p-en
Requires-Dist: jieba
Requires-Dist: jieba-fast
Requires-Dist: pypinyin
Requires-Dist: pynini
Requires-Dist: importlib-resources
Requires-Dist: langid
